fastapi_batteries/__init__.py
fastapi_batteries/py.typed
fastapi_batteries/alembic/utils.py
fastapi_batteries/crud/__init__.py
fastapi_batteries/fastapi/utils.py
fastapi_batteries/fastapi/deps/file_validator.py
fastapi_batteries/fastapi/exceptions/api_exception.py
fastapi_batteries/fastapi/middlewares/__init__.py
fastapi_batteries/fastapi/middlewares/query_count.py
fastapi_batteries/fastapi/middlewares/request_process_time.py
fastapi_batteries/pydantic/schemas.py
fastapi_batteries/sa/mixins.py
fastapi_batteries/utils/file.py
fastapi_batteries/utils/mimetypes_utils.py
fastapi_batteries/utils/pagination.py
fastapi_batteries/utils/size.py
fastapi_batteries/utils/types_utils.py
fastapi_batteries-0.3.0.dist-info/METADATA
fastapi_batteries-0.3.0.dist-info/WHEEL
fastapi_batteries-0.3.0.dist-info/entry_points.txt
fastapi_batteries-0.3.0.dist-info/RECORD
