Metadata-Version: 2.3
Name: fastapi-batteries
Version: 0.3.0
Summary: Add your description here
Author-email: JD Solanki <jdsolanki0001@gmail.com>
Requires-Python: >=3.13
Requires-Dist: email-validator>=2.2.0
Requires-Dist: python-magic>=0.4.27
